thebestastlibrary/__inint__.py
thebestastlibrary/fibonacci.py
thebestastlibrary/main.py
thebestastlibrary/visitor.py
thebestastlibrary-0.5.dist-info/LICENSE
thebestastlibrary-0.5.dist-info/METADATA
thebestastlibrary-0.5.dist-info/WHEEL
thebestastlibrary-0.5.dist-info/top_level.txt
thebestastlibrary-0.5.dist-info/RECORD
