Metadata-Version: 2.1
Name: thebestastlibrary
Version: 0.5
Summary: Library for vizualizing ast.
Home-page: https://github.com/JaneKirillova/advanced-python/tree/main/hw_1
Author: Evgeniia Kirillova
Author-email: grindevald666@gmail.com
License: UNKNOWN
Platform: UNKNOWN
License-File: LICENSE
Requires-Dist: networkx (==2.5.1)
Requires-Dist: pydot (==1.4.2)
